LICENSE
README.md
pyproject.toml
setup.py
DeepCell_Toolbox.egg-info/PKG-INFO
DeepCell_Toolbox.egg-info/SOURCES.txt
DeepCell_Toolbox.egg-info/dependency_links.txt
DeepCell_Toolbox.egg-info/requires.txt
DeepCell_Toolbox.egg-info/top_level.txt
deepcell_toolbox/__init__.py
deepcell_toolbox/__version__.py
deepcell_toolbox/compute_overlap.pyx
deepcell_toolbox/deep_watershed.py
deepcell_toolbox/deep_watershed_test.py
deepcell_toolbox/metrics.py
deepcell_toolbox/metrics_test.py
deepcell_toolbox/processing.py
deepcell_toolbox/processing_test.py
deepcell_toolbox/utils.py
deepcell_toolbox/utils_test.py