Metadata-Version: 2.1
Name: DeepCell-Toolbox
Version: 0.11.1
Summary: The pre- and post-processing functions module for deepcell-tf.
Home-page: https://github.com/vanvalenlab/deepcell-toolbox
Author: Van Valen Lab
Author-email: vanvalenlab@gmail.com
License: LICENSE
Download-URL: https://github.com/vanvalenlab/deepcell-toolbox/tarball/0.11.1
Platform: UNKNOWN
Classifier: Programming Language :: Python
Classifier: Programming Language :: Python :: 3
Classifier: Programming Language :: Python :: 3.6
Classifier: Programming Language :: Python :: 3.7
Classifier: Programming Language :: Python :: 3.8
Classifier: Programming Language :: Python :: 3.9
Requires-Python: >=3.6, <3.10
Provides-Extra: tests
